Workbook

Sheet README
A1: Excel Practice — Phase 1: Data Analytics
A3: Purpose | B3: Practice Excel fundamentals, formulas, data cleaning, dates, Pivot Tables, charts, slicers concepts, and Power Query concepts.
A5: Sheets
A6: 01_Raw_Sales | B6: Raw e-commerce dataset
A7: 02_Basic_Formulas | B7: SUM, AVERAGE, COUNT, COUNTA, MIN, MAX
A8: 03_IF_Logic | B8: IF-based classification
A9: 04_SUMIF_COUNTIF | B9: Conditional aggregation
A10: 05_SUMIFS_COUNTIFS | B10: Multiple-condition analysis
A11: 06_XLOOKUP | B11: Product lookup example
A12: 07_Data_Cleaning | B12: TRIM, CLEAN, UPPER, LOWER, PROPER, duplicates
A13: 08_Dates | B13: YEAR, MONTH, DAY and monthly analysis
A14: 09_Pivot_Data | B14: Pivot-ready employee dataset
A15: 10_Dashboard | B15: KPI summary and chart
A16: 11_Power_Query_Guide | B16: Power Query workflow guide
A17: 12_Practice_Questions | B17: Exercises to solve independently

Sheet 01_Raw_Sales
A1: Order ID | B1: Date | C1: Customer | D1: Product ID | E1: Product | F1: City | G1: Sales | H1: Profit
A2: 1001 | B2: 2026-01-03 | C2: Ali | D2: P01 | E2: Laptop | F2: Lahore | G2: 120000 | H2: 15000
A3: 1002 | B3: 2026-01-08 | C3: Sara | D3: P02 | E3: Mouse | F3: Karachi | G3: 5000 | H3: 1200
A4: 1003 | B4: 2026-01-15 | C4: Ahmed | D4: P01 | E4: Laptop | F4: Lahore | G4: 110000 | H4: 13000
A5: 1004 | B5: 2026-02-02 | C5: Ayesha | D5: P03 | E5: Keyboard | F5: Islamabad | G5: 8000 | H5: 2000
A6: 1005 | B6: 2026-02-11 | C6: Hamza | D6: P02 | E6: Mouse | F6: Lahore | G6: 6000 | H6: 1500
A7: 1006 | B7: 2026-02-19 | C7: Zainab | D7: P04 | E7: Monitor | F7: Karachi | G7: 45000 | H7: 7000
A8: 1007 | B8: 2026-03-04 | C8: Bilal | D8: P03 | E8: Keyboard | F8: Lahore | G8: 9000 | H8: 2200
A9: 1008 | B9: 2026-03-12 | C9: Hina | D9: P04 | E9: Monitor | F9: Islamabad | G9: 50000 | H9: 8500
A10: 1009 | B10: 2026-03-20 | C10: Usman | D10: P01 | E10: Laptop | F10: Karachi | G10: 125000 | H10: 16000
A11: 1010 | B11: 2026-04-05 | C11: Maham | D11: P02 | E11: Mouse | F11: Lahore | G11: 7000 | H11: 1700

Sheet 02_Basic_Formulas
A1: Metric | B1: Formula | C1: Result
A2: Total Sales | B2: =SUM('01_Raw_Sales'!G2:G11) | C2: =SUM('01_Raw_Sales'!G2:G11)
A3: Average Sales | B3: =AVERAGE('01_Raw_Sales'!G2:G11) | C3: =AVERAGE('01_Raw_Sales'!G2:G11)
A4: Order Count | B4: =COUNT('01_Raw_Sales'!G2:G11) | C4: =COUNT('01_Raw_Sales'!G2:G11)
A5: Customer Count (non-empty) | B5: =COUNTA('01_Raw_Sales'!C2:C11) | C5: =COUNTA('01_Raw_Sales'!C2:C11)
A6: Minimum Sale | B6: =MIN('01_Raw_Sales'!G2:G11) | C6: =MIN('01_Raw_Sales'!G2:G11)
A7: Maximum Sale | B7: =MAX('01_Raw_Sales'!G2:G11) | C7: =MAX('01_Raw_Sales'!G2:G11)

Sheet 03_IF_Logic
A1: Customer | B1: Experience (Years) | C1: Level Formula | D1: Level
A2: Ali | B2: 2 | C2: =IF(B2>=4,"Senior","Junior") | D2: =IF(B2>=4,"Senior","Junior")
A3: Sara | B3: 3 | C3: =IF(B3>=4,"Senior","Junior") | D3: =IF(B3>=4,"Senior","Junior")
A4: Ahmed | B4: 5 | C4: =IF(B4>=4,"Senior","Junior") | D4: =IF(B4>=4,"Senior","Junior")
A5: Ayesha | B5: 4 | C5: =IF(B5>=4,"Senior","Junior") | D5: =IF(B5>=4,"Senior","Junior")
A6: Hamza | B6: 3 | C6: =IF(B6>=4,"Senior","Junior") | D6: =IF(B6>=4,"Senior","Junior")
A7: Zainab | B7: 2 | C7: =IF(B7>=4,"Senior","Junior") | D7: =IF(B7>=4,"Senior","Junior")

Sheet 04_SUMIF_COUNTIF
A1: Question | B1: Formula | C1: Result
A2: Lahore total sales | B2: =SUMIF('01_Raw_Sales'!F2:F11,"Lahore",'01_Raw_Sales'!G2:G11) | C2: =SUMIF('01_Raw_Sales'!F2:F11,"Lahore",'01_Raw_Sales'!G2:G11)
A3: Lahore order count | B3: =COUNTIF('01_Raw_Sales'!F2:F11,"Lahore") | C3: =COUNTIF('01_Raw_Sales'!F2:F11,"Lahore")

Sheet 05_SUMIFS_COUNTIFS
A1: Question | B1: Formula | C1: Result
A2: Lahore Laptop sales | B2: =SUMIFS('01_Raw_Sales'!G2:G11,'01_Raw_Sales'!F2:F11,"Lahore",'01_Raw_Sales'!E2:E11,"Laptop") | C2: =SUMIFS('01_Raw_Sales'!G2:G11,'01_Raw_Sales'!F2:F11,"Lahore",'01_Raw_Sales'!E2:E11,"Laptop")
A3: Karachi Mouse order count | B3: =COUNTIFS('01_Raw_Sales'!F2:F11,"Karachi",'01_Raw_Sales'!E2:E11,"Mouse") | C3: =COUNTIFS('01_Raw_Sales'!F2:F11,"Karachi",'01_Raw_Sales'!E2:E11,"Mouse")

Sheet 06_XLOOKUP
A1: Product ID | B1: Product | C1: Price | E1: Order Product ID | F1: XLOOKUP Formula | G1: Returned Product
A2: P01 | B2: Laptop | C2: 120000 | E2: P01 | F2: =XLOOKUP(E2,A2:A5,B2:B5,"Not Found") | G2: =XLOOKUP(E2,A2:A5,B2:B5,"Not Found")
A3: P02 | B3: Mouse | C3: 5000 | E3: P02 | F3: =XLOOKUP(E3,A2:A5,B2:B5,"Not Found") | G3: =XLOOKUP(E3,A2:A5,B2:B5,"Not Found")
A4: P03 | B4: Keyboard | C4: 8000
A5: P04 | B5: Monitor | C5: 45000

Sheet 07_Data_Cleaning
A1: Raw City | B1: TRIM | C1: UPPER | D1: LOWER | E1: PROPER | G1: Cleaning Checklist
A2: Lahore | B2: =TRIM(A2) | C2: =UPPER(A2) | D2: =LOWER(A2) | E2: =PROPER(A2) | G2: Remove duplicates
A3: lahore | B3: =TRIM(A3) | C3: =UPPER(A3) | D3: =LOWER(A3) | E3: =PROPER(A3) | G3: Handle missing values
A4: LAHORE | B4: =TRIM(A4) | C4: =UPPER(A4) | D4: =LOWER(A4) | E4: =PROPER(A4) | G4: Standardize text
A5: Karachi | B5: =TRIM(A5) | C5: =UPPER(A5) | D5: =LOWER(A5) | E5: =PROPER(A5) | G5: Check data types
A6: ISLAMABAD | B6: =TRIM(A6) | C6: =UPPER(A6) | D6: =LOWER(A6) | E6: =PROPER(A6) | G6: Check outliers

Sheet 08_Dates
A1: Date | B1: YEAR | C1: MONTH | D1: DAY | E1: Month Name
A2: 2026-01-03 | B2: =YEAR(A2) | C2: =MONTH(A2) | D2: =DAY(A2) | E2: =TEXT(A2,"mmmm")
A3: 2026-01-08 | B3: =YEAR(A3) | C3: =MONTH(A3) | D3: =DAY(A3) | E3: =TEXT(A3,"mmmm")
A4: 2026-01-15 | B4: =YEAR(A4) | C4: =MONTH(A4) | D4: =DAY(A4) | E4: =TEXT(A4,"mmmm")
A5: 2026-02-02 | B5: =YEAR(A5) | C5: =MONTH(A5) | D5: =DAY(A5) | E5: =TEXT(A5,"mmmm")
A6: 2026-02-11 | B6: =YEAR(A6) | C6: =MONTH(A6) | D6: =DAY(A6) | E6: =TEXT(A6,"mmmm")
A7: 2026-02-19 | B7: =YEAR(A7) | C7: =MONTH(A7) | D7: =DAY(A7) | E7: =TEXT(A7,"mmmm")
A8: 2026-03-04 | B8: =YEAR(A8) | C8: =MONTH(A8) | D8: =DAY(A8) | E8: =TEXT(A8,"mmmm")
A9: 2026-03-12 | B9: =YEAR(A9) | C9: =MONTH(A9) | D9: =DAY(A9) | E9: =TEXT(A9,"mmmm")
A10: 2026-03-20 | B10: =YEAR(A10) | C10: =MONTH(A10) | D10: =DAY(A10) | E10: =TEXT(A10,"mmmm")
A11: 2026-04-05 | B11: =YEAR(A11) | C11: =MONTH(A11) | D11: =DAY(A11) | E11: =TEXT(A11,"mmmm")

Sheet 09_Pivot_Data
A1: Employee | B1: Department | C1: Salary | D1: Experience
A2: Ali | B2: IT | C2: 80000 | D2: 2
A3: Sara | B3: HR | C3: 70000 | D3: 3
A4: Ahmed | B4: IT | C4: 120000 | D4: 5
A5: Ayesha | B5: Marketing | C5: 90000 | D5: 4
A6: Hamza | B6: IT | C6: 100000 | D6: 3
A7: Zainab | B7: HR | C7: 75000 | D7: 2

Sheet 10_Dashboard
A1: Excel Analytics Dashboard
A3: KPI | B3: Value | D3: City | E3: Sales
A4: Total Sales | B4: =SUM('01_Raw_Sales'!G2:G11) | D4: Lahore | E4: =SUMIF('01_Raw_Sales'!F2:F11,D4,'01_Raw_Sales'!G2:G11)
A5: Total Profit | B5: =SUM('01_Raw_Sales'!H2:H11) | D5: Karachi | E5: =SUMIF('01_Raw_Sales'!F2:F11,D5,'01_Raw_Sales'!G2:G11)
A6: Average Order Value | B6: =AVERAGE('01_Raw_Sales'!G2:G11) | D6: Islamabad | E6: =SUMIF('01_Raw_Sales'!F2:F11,D6,'01_Raw_Sales'!G2:G11)
A7: Number of Orders | B7: =COUNT('01_Raw_Sales'!G2:G11)

Sheet 11_Power_Query_Guide
A1: Step | B1: What to do | C1: Example
A2: 1 | B2: Data → Get Data | C2: Import CSV/Excel files
A3: 2 | B3: Transform Data | C3: Open Power Query Editor
A4: 3 | B4: Clean | C4: Remove duplicates, trim text, replace values
A5: 4 | B5: Transform | C5: Change data types, split/merge columns
A6: 5 | B6: Combine | C6: Append monthly files or merge related tables
A7: 6 | B7: Load | C7: Load clean data into Excel
A8: 7 | B8: Refresh | C8: Use Refresh All when new data arrives

Sheet 12_Practice_Questions
A1: Practice Questions
A3: 1. Calculate total sales using SUM.
A4: 2. Calculate average sales using AVERAGE.
A5: 3. Find minimum and maximum sales.
A6: 4. Count the number of orders.
A7: 5. Calculate Lahore total sales using SUMIF.
A8: 6. Count Lahore orders using COUNTIF.
A9: 7. Calculate Lahore Laptop sales using SUMIFS.
A10: 8. Use IF to classify orders as High if Sales >= 50000, otherwise Low.
A11: 9. Use XLOOKUP to return a product name from Product ID.
A12: 10. Clean the city column using TRIM/PROPER.
A13: 11. Extract year and month from the Date column.
... A17: 15. Write 3 business insights from the dataset.
